one_doc/__init__.py
one_doc/auth.py
one_doc/errors.py
one_doc/main.py
one_doc/main_async.py
one_doc/response.py
one_doc/schemas.py
one_doc-0.1.1.dist-info/METADATA
one_doc-0.1.1.dist-info/WHEEL
one_doc-0.1.1.dist-info/RECORD
