Metadata-Version: 2.1
Name: one_doc
Version: 0.1.1
Summary: Python SDK generated by Sideko (sideko.dev)
Requires-Python: >=3.8,<4.0
Classifier: Programming Language :: Python :: 3
Classifier: Programming Language :: Python :: 3.8
Classifier: Programming Language :: Python :: 3.9
Classifier: Programming Language :: Python :: 3.10
Classifier: Programming Language :: Python :: 3.11
Classifier: Programming Language :: Python :: 3.12
Requires-Dist: httpx (>=0.25.2,<0.26.0)
Requires-Dist: pydantic (>=2.4.2,<3.0.0)
Requires-Dist: python-dateutil (>=2.8.2,<3.0.0)
